HISTORY.rst
LICENSE
MANIFEST.in
README.rst
setup.py
pyTOP/__init__.py
pyTOP/api.py
pyTOP/campaign.py
pyTOP/category.py
pyTOP/crm.py
pyTOP/errors.py
pyTOP/favorite.py
pyTOP/fenxiao.py
pyTOP/increment.py
pyTOP/insight.py
pyTOP/item.py
pyTOP/logistics.py
pyTOP/sellercenter.py
pyTOP/shop.py
pyTOP/systime.py
pyTOP/taobaoke.py
pyTOP/trade.py
pyTOP/traderate.py
pyTOP/user.py
pyTOP/vas.py
pyTOP/wangwang.py
pyTOP.egg-info/.DS_Store
pyTOP.egg-info/PKG-INFO
pyTOP.egg-info/SOURCES.txt
pyTOP.egg-info/dependency_links.txt
pyTOP.egg-info/requires.txt
pyTOP.egg-info/top_level.txt
pyTOP/packages/__init__.py
pyTOP/packages/requests/__init__.py
pyTOP/packages/requests/api.py
pyTOP/packages/requests/async.py
pyTOP/packages/requests/auth.py
pyTOP/packages/requests/defaults.py
pyTOP/packages/requests/exceptions.py
pyTOP/packages/requests/hooks.py
pyTOP/packages/requests/models.py
pyTOP/packages/requests/monkeys.py
pyTOP/packages/requests/sessions.py
pyTOP/packages/requests/status_codes.py
pyTOP/packages/requests/structures.py
pyTOP/packages/requests/utils.py
pyTOP/packages/requests/packages/urllib3/__init__.py
pyTOP/packages/requests/packages/urllib3/_collections.py
pyTOP/packages/requests/packages/urllib3/connectionpool.py
pyTOP/packages/requests/packages/urllib3/exceptions.py
pyTOP/packages/requests/packages/urllib3/filepost.py
pyTOP/packages/requests/packages/urllib3/poolmanager.py
pyTOP/packages/requests/packages/urllib3/request.py
pyTOP/packages/requests/packages/urllib3/response.py