Metadata-Version: 1.0
Name: pyTOP
Version: 0.1.1
Summary: Taobao Open Platform API Python Wrapper.
Home-page: http://www.github.com/bububa/pyTOP
Author: Syd Xu
Author-email: prof.syd.xu@gmail.com
License: ISC
Platform: UNKNOWN
Classifier: Development Status :: 3 - Alpha
Classifier: Intended Audience :: Developers
Classifier: Natural Language :: English
Classifier: License :: OSI Approved :: ISC License (ISCL)
Classifier: Programming Language :: Python
Classifier: Programming Language :: Python :: 2.5
Classifier: Programming Language :: Python :: 2.6
Classifier: Programming Language :: Python :: 2.7
